nanite/__init__.py
nanite/_version.py
nanite/fit.py
nanite/group.py
nanite/indent.py
nanite/poc.py
nanite/preproc.py
nanite/qmap.py
nanite/read.py
nanite/smooth.py
nanite/cli/__init__.py
nanite/cli/plotting.py
nanite/cli/profile.py
nanite/cli/rating.py
nanite/model/__init__.py
nanite/model/core.py
nanite/model/logic.py
nanite/model/model_conical_indenter.py
nanite/model/model_hertz_paraboloidal.py
nanite/model/model_hertz_three_sided_pyramid.py
nanite/model/model_power_layer_clifford_2009.py
nanite/model/model_sneddon_spherical_approximation.py
nanite/model/residuals.py
nanite/model/weight.py
nanite/rate/__init__.py
nanite/rate/features.py
nanite/rate/io.py
nanite/rate/rater.py
nanite/rate/regressors.py
nanite/rate/ts_zef18/train_feat_bin_apr_spikes_count.txt
nanite/rate/ts_zef18/train_feat_bin_cp_position.txt
nanite/rate/ts_zef18/train_feat_bin_size.txt
nanite/rate/ts_zef18/train_feat_con_apr_flatness.txt
nanite/rate/ts_zef18/train_feat_con_apr_size.txt
nanite/rate/ts_zef18/train_feat_con_apr_sum.txt
nanite/rate/ts_zef18/train_feat_con_bln_slope.txt
nanite/rate/ts_zef18/train_feat_con_bln_variation.txt
nanite/rate/ts_zef18/train_feat_con_cp_curvature.txt
nanite/rate/ts_zef18/train_feat_con_cp_magnitude.txt
nanite/rate/ts_zef18/train_feat_con_idt_maxima_75perc.txt
nanite/rate/ts_zef18/train_feat_con_idt_monotony.txt
nanite/rate/ts_zef18/train_feat_con_idt_spike_area.txt
nanite/rate/ts_zef18/train_feat_con_idt_sum.txt
nanite/rate/ts_zef18/train_feat_con_idt_sum_75perc.txt
nanite/rate/ts_zef18/train_response.txt
nanite-4.2.2.dist-info/licenses/LICENSE
nanite-4.2.2.dist-info/METADATA
nanite-4.2.2.dist-info/WHEEL
nanite-4.2.2.dist-info/entry_points.txt
nanite-4.2.2.dist-info/top_level.txt
nanite-4.2.2.dist-info/RECORD
