Metadata-Version: 2.4
Name: nanite
Version: 4.2.2
Summary: Loading, fitting, and rating AFM force-distance data
Author: Paul Müller, Shada Abuhattum
Maintainer-email: Paul Müller <dev@craban.de>
License: GPL version 3
Project-URL: source, https://github.com/AFM-Analysis/nanite
Project-URL: tracker, https://github.com/AFM-Analysis/nanite/issues
Project-URL: documentation, https://nanite.readthedocs.io/en/stable/
Project-URL: changelog, https://nanite.readthedocs.io/en/stable/sec_changelog.html
Keywords: atomic force microscopy,mechanical phenotyping,tissue analysis
Classifier: Operating System :: OS Independent
Classifier: Programming Language :: Python :: 3
Classifier: Topic :: Scientific/Engineering :: Visualization
Classifier: Intended Audience :: Science/Research
Requires-Python: <4,>=3.10
License-File: LICENSE
Requires-Dist: afmformats>=0.16.4
Requires-Dist: h5py>=3.9.0
Requires-Dist: lmfit>=1
Requires-Dist: numpy>=1.22.0
Requires-Dist: scikit-learn>=0.23.0
Requires-Dist: scipy>=1.10.0
Provides-Extra: cli
Requires-Dist: appdirs; extra == "cli"
Requires-Dist: matplotlib>=2.2.2; extra == "cli"
Requires-Dist: tifffile>=0.15.0; extra == "cli"
Provides-Extra: aca
Requires-Dist: nanite_model_sneddon_spher<2.0,>=1.0; extra == "aca"
Provides-Extra: all
Requires-Dist: nanite[ACA,CLI]; extra == "all"
Dynamic: license-file
